{
  "fix_commits": [],
  "generated_at": "2026-07-15T13:36:30.408037+00:00",
  "kind": "problem_summary",
  "linked_incident_ids": [
    "inc-demo-session"
  ],
  "next_review_ts": null,
  "occurrence_count": 59,
  "owner_actor": "github_sync",
  "problem_id": "problem-9e338df241c5",
  "recurred_after_fix": false,
  "schema_version": 1,
  "source": {
    "digest": "sha256:7681839a61b53ad966141fc7c3e8d365152a9eab614f18a81fec998675267e80",
    "last_seq": 503,
    "projection": "problems"
  },
  "status": "open",
  "summary_text": "problem-9e338df241c5: repair-data outcome=discord_escalated plan=demo-plan kind=chain workspace=/tmp/workspace"
}
