{
  "fix_commits": [],
  "generated_at": "2026-07-08T13:33:01.593980+00:00",
  "kind": "problem_summary",
  "linked_incident_ids": [
    "inc-megaplan-native-parity-corrective"
  ],
  "next_review_ts": null,
  "occurrence_count": 6,
  "owner_actor": "github_sync",
  "problem_id": "problem-55b5ebf18290",
  "recurred_after_fix": false,
  "schema_version": 1,
  "source": {
    "digest": "sha256:3b7e9cef70338585541d809437fe26a01d3db796456344be0b30bfce52396c80",
    "last_seq": 236,
    "projection": "problems"
  },
  "status": "open",
  "summary_text": "problem-55b5ebf18290: stale_active_step: plan=s3-tiebreaker-and-replan-20260706-0044; state=initialized; phase=plan; worker_pid=287069 not live"
}
