{
  "fix_commits": [],
  "generated_at": "2026-07-14T07:42:30.648889+00:00",
  "kind": "problem_summary",
  "linked_incident_ids": [
    "inc-workflow-boundary-contracts-corrective-20260710"
  ],
  "next_review_ts": null,
  "occurrence_count": 21,
  "owner_actor": "github_sync",
  "problem_id": "problem-461ac04158b3",
  "recurred_after_fix": false,
  "schema_version": 1,
  "source": {
    "digest": "sha256:74c5329dcb48bf335e8bb495588fbdf9b85cbf7146b88becba3d9381ac27a6fa",
    "last_seq": 478,
    "projection": "problems"
  },
  "status": "open",
  "summary_text": "problem-461ac04158b3: repair-data outcome=repair_exhausted kind=chain workspace=/workspace/workflow-boundary-contracts-corrective-20260710/Arnold"
}
