{
  "fix_commits": [],
  "generated_at": "2026-07-15T07:36:20.503491+00:00",
  "kind": "problem_summary",
  "linked_incident_ids": [
    "inc-demo-session"
  ],
  "next_review_ts": null,
  "occurrence_count": 3,
  "owner_actor": "github_sync",
  "problem_id": "problem-6a1177eb343e",
  "recurred_after_fix": false,
  "schema_version": 1,
  "source": {
    "digest": "sha256:13d41280f1b49a1fa30fff4c38d9b3f0ce3afb5ea9f83705f7a6a23de6ff190e",
    "last_seq": 499,
    "projection": "problems"
  },
  "status": "open",
  "summary_text": "problem-6a1177eb343e: managed automatic_meta_repair execution started"
}
