{
  "fix_commits": [],
  "generated_at": "2026-07-04T19:30:40.054907+00:00",
  "kind": "problem_summary",
  "linked_incident_ids": [
    "inc-megaplan-chain-reigh-extension-composition-spine-epic-12d49a3e"
  ],
  "next_review_ts": null,
  "occurrence_count": 4,
  "owner_actor": "watchdog",
  "problem_id": "problem-71f954a05546",
  "recurred_after_fix": false,
  "schema_version": 1,
  "source": {
    "digest": "sha256:bd0888167523154db74c22a38aba6da50a577cee6b52f771b6101a9bda2ee152",
    "last_seq": 5,
    "projection": "problems"
  },
  "status": "open",
  "summary_text": "problem-71f954a05546: progress_stall:m4-clip-type-shader-and-20260704-0427:iteration=1:attempt=0:plan_v_count=1:events_stale=11m"
}
