{
  "id": "log_4e5be710a440",
  "level": "debug",
  "category": "system",
  "event_type": "authority_divergence",
  "message": "authority_divergence emitted",
  "details": {
    "event": {
      "seq": 6727,
      "schema_version": 1,
      "ts_utc": "2026-06-20T19:05:31.810840+00:00",
      "ts_rel_init_s": 8106.28393,
      "kind": "authority_divergence",
      "phase": "execute",
      "payload": {
        "diagnostic_version": 1,
        "task_id": "T13",
        "raw_terminal_status": "done",
        "authority_status": "unknown",
        "authoritative": false,
        "reason": "stale_evidence:missing_head:task_commands_run",
        "missing_outputs": [],
        "stale_evidence": [
          "missing_head:task_commands_run",
          "missing_head:task_commands_run",
          "missing_head:task_commands_run",
          "missing_head:task_commands_run",
          "missing_head:task_commands_run",
          "missing_head:task_commands_run",
          "missing_head:task_commands_run",
          "missing_head:task_commands_run",
          "missing_head:task_commands_run",
          "missing_head:task_commands_run",
          "missing_head:task_commands_run",
          "missing_head:task_commands_run",
          "missing_head:task_commands_run",
          "missing_head:task_commands_run",
          "missing_head:task_commands_run",
          "missing_head:task_commands_run",
          "missing_head:task_commands_run",
          "missing_head:task_commands_run",
          "missing_head:task_commands_run"
        ],
        "would_block_reasons": [
          "stale_evidence:missing_head:task_commands_run"
        ],
        "error": null,
        "diagnostics": {
          "task_id": "T13",
          "declared_outputs": {
            "commands_run": [
              "python3 -m pytest vendor/timeline-schema/tests/ --tb=short -q --no-header",
              "npx vitest run --config config/testing/vitest.config.ts src/sdk/examples-governance.test.ts --reporter=verbose",
              "npx vitest run --config config/testing/vitest.config.ts src/sdk/__tests__/sdk-boundary.test.ts --reporter=verbose",
              "npx vitest run --config config/testing/vitest.config.ts src/sdk/index.test.ts --reporter=verbose",
              "npx vitest run --config config/testing/vitest.config.ts src/sdk/extensionSettingsService.test.ts src/sdk/extensionSettingsMigration.test.ts --reporter=verbose",
              "npx vitest run --config config/testing/vitest.config.ts src/tools/video-editor/examples/extensions/__tests__/flagship-local-transition.test.ts src/tools/video-editor/examples/extensions/__tests__/live-webcam-canary.test.ts src/tools/video-editor/examples/extensions/__tests__/live-generated-frame-canary.test.ts --reporter=verbose",
              "npx tsc --noEmit"
            ]
          },
          "linked_evidence_count": 38,
          "evidence_count": 250,
          "normalization": "iterable",
          "status": "unknown",
          "evidence_sources": [
            "plan_artifacts"
          ],
          "loaded_evidence_count": 250,
          "raw_terminal_status": "done"
        },
        "ts_utc": "2026-06-20T19:05:31.810393+00:00"
      },
      "transaction_id": "61abfbfc1ef392a4",
      "store_method": "log_system_event"
    }
  },
  "turn_id": null,
  "epic_id": "m15-hardening-compatibility-20260620-1850",
  "occurred_at": "2026-06-20T19:05:31.810886Z"
}
