{
  "id": "log_79e15d3732bf",
  "level": "debug",
  "category": "system",
  "event_type": "authority_divergence",
  "message": "authority_divergence emitted",
  "details": {
    "event": {
      "seq": 3129,
      "schema_version": 1,
      "ts_utc": "2026-06-19T18:41:05.481557+00:00",
      "ts_rel_init_s": 3437.293594,
      "kind": "authority_divergence",
      "phase": "execute",
      "payload": {
        "diagnostic_version": 1,
        "task_id": "T12",
        "raw_terminal_status": "skipped",
        "authority_status": "unknown",
        "authoritative": false,
        "reason": "missing_linked_evidence",
        "missing_outputs": [],
        "stale_evidence": [],
        "would_block_reasons": [
          "missing_linked_evidence"
        ],
        "error": null,
        "diagnostics": {
          "task_id": "T12",
          "declared_outputs": {},
          "linked_evidence_count": 0,
          "evidence_count": 42,
          "normalization": "iterable",
          "status": "unknown",
          "evidence_sources": [
            "plan_artifacts"
          ],
          "loaded_evidence_count": 42,
          "raw_terminal_status": "skipped"
        },
        "ts_utc": "2026-06-19T18:41:05.481232+00:00"
      },
      "transaction_id": "21889183105389fb",
      "store_method": "log_system_event"
    }
  },
  "turn_id": null,
  "epic_id": "handoff-artifacts-exact-20260619-1943",
  "occurred_at": "2026-06-19T18:41:05.481586Z"
}
