{
  "id": "log_94fc71f442ae",
  "level": "debug",
  "category": "system",
  "event_type": "authority_divergence",
  "message": "authority_divergence emitted",
  "details": {
    "event": {
      "seq": 3251,
      "schema_version": 1,
      "ts_utc": "2026-06-20T18:00:04.690900+00:00",
      "ts_rel_init_s": 4179.16399,
      "kind": "authority_divergence",
      "phase": "execute",
      "payload": {
        "diagnostic_version": 1,
        "task_id": "T10",
        "raw_terminal_status": "done",
        "authority_status": "unknown",
        "authoritative": false,
        "reason": "stale_evidence:missing_head:task_files_changed",
        "missing_outputs": [],
        "stale_evidence": [
          "missing_head:task_files_changed"
        ],
        "would_block_reasons": [
          "stale_evidence:missing_head:task_files_changed"
        ],
        "error": null,
        "diagnostics": {
          "task_id": "T10",
          "declared_outputs": {
            "files_changed": [
              "docs/video-editor/provider-compatibility-matrix.md"
            ]
          },
          "linked_evidence_count": 2,
          "evidence_count": 98,
          "normalization": "iterable",
          "status": "unknown",
          "evidence_sources": [
            "plan_artifacts"
          ],
          "loaded_evidence_count": 98,
          "raw_terminal_status": "done"
        },
        "ts_utc": "2026-06-20T18:00:04.690124+00:00"
      },
      "transaction_id": "5eb773c4018713bf",
      "store_method": "log_system_event"
    }
  },
  "turn_id": null,
  "epic_id": "m15-hardening-compatibility-20260620-1850",
  "occurred_at": "2026-06-20T18:00:04.690960Z"
}
