{
  "schema_version": 0,
  "current_milestone_index": 1,
  "current_plan_name": "m1a-reference-identity-patch-20260702-1603",
  "current_milestone_base_sha": null,
  "target_base_ref": "4c348280f180be93c56efdb1ea9a6a5e2a4bfa4b",
  "last_state": "prepped",
  "pr_number": 77,
  "pr_state": "open",
  "completed": [
    {
      "label": "m0-decisions-fixtures",
      "plan": "m0-decisions-fixtures-and-20260701-1826",
      "status": "done",
      "pr_number": 76,
      "pr_state": "merged"
    }
  ],
  "branch_head": "ae863c5db2e682fd54eec70281f4f6d61200bd18",
  "pr_head": "1271da46bf96a19167b02212fc3c47c8610bb9e4",
  "last_pushed_commit": "ae863c5db2e682fd54eec70281f4f6d61200bd18",
  "dirty_flag": true,
  "sync_state": "dirty",
  "extra_repos": [],
  "chain_session": null,
  "resolved_workspace": null,
  "extra_repo_sync": [],
  "completion_contract_mode": "shadow",
  "full_suite_backstop_mode": "shadow",
  "retry_counts": {},
  "ladder_stage": {},
  "profile_bumps": {},
  "robustness_bumps": {},
  "depth_bumps": {},
  "enforce_revise_counts": {},
  "metadata": {
    "chain_spec_path": "/workspace/reigh-extension-composition-spine-epic-12d49a3e/reigh-app/.megaplan/initiatives/reigh-extension-composition-spine-epic/chain.yaml",
    "chain_spec_sha256": "11ab4cde1fd4bd4781cc65af9f0b6288c9a1ac1d8c15274e8bd0f087f4bcf32e",
    "execution_environment": {
      "created_phase": "chain_start",
      "engine_root": "/workspace/arnold",
      "last_observed_phase": "chain_start",
      "project_root": "/workspace/reigh-extension-composition-spine-epic-12d49a3e/reigh-app",
      "schema_version": 1,
      "target_base": null,
      "target_base_ref": "main",
      "target_fallback_reason": "merge_base_unavailable:main",
      "target_head": "e19485769b0c0e515d6df630f78cafc09f57ad20",
      "target_root": "/workspace/reigh-extension-composition-spine-epic-12d49a3e/reigh-app",
      "work_dir": "/workspace/reigh-extension-composition-spine-epic-12d49a3e/reigh-app"
    },
    "ground_truth_reconciliation": {
      "reconciled_at": "2026-07-02T16:14:20Z",
      "plan": "m1a-reference-identity-patch-20260702-1603",
      "current_state": "prepped",
      "latest_failure": null,
      "last_gate": {},
      "active_step": null,
      "pr_number": 77,
      "pr_state": "open"
    },
    "operator_recovery_20260702": {
      "previous_current_plan_name": "m0-decisions-fixtures-and-20260701-1826",
      "previous_last_state": "critiqued",
      "reason": "retry after GitHub large-file push rejection from runtime event journal"
    },
    "operator_recovery_20260702_done_replay": {
      "previous_last_state": "failed",
      "reason": "review phase had successful phase_result and transition_decision_review_done; replay post-milestone transition"
    }
  }
}
